{
  "total": 39,
  "public": 39,
  "private": 0,
  "total_views": 28,
  "issues": [],
  "public_videos": [
    {
      "id": "mReDNz-Exdk",
      "title": "Soundie: Lamp of Memory | 8K HQ (4K UHD) | Vintage Music Film | @remAIke_IT",
      "views": 9,
      "tags": [
        "1940s",
        "1940s music",
        "4K UHD",
        "8K",
        "AI upscaled",
        "Lamp of Memory",
        "big band",
        "classic music",
        "jazz",
        "jukebox",
        "music video",
        "nostalgia",
        "panoram",
        "public domain",
        "remAIke",
        "remastered",
        "retro",
        "soundie",
        "soundies",
        "swing",
        "vintage music"
      ]
    },
    {
      "id": "6XVj6G3qNYY",
      "title": "Soundie: Jiveroo | 8K HQ (4K UHD) | Vintage Music Film | @remAIke_IT",
      "views": 5,
      "tags": [
        "1940s",
        "1940s music",
        "4K UHD",
        "8K",
        "Mills Novelty Company",
        "Official Audio",
        "Panoram",
        "Soundie",
        "Soundies",
        "big band",
        "big band music",
        "boogie woogie",
        "classic music",
        "dance",
        "golden age music",
        "jazz",
        "jazz music",
        "jazz standard",
        "jive",
        "jukebox",
        "music",
        "music video",
        "official video",
        "remAIke",
        "remastered",
        "restored",
        "retro music",
        "rhythm and blues",
        "song",
        "swing dance",
        "swing era",
        "swing music",
        "vintage music",
        "vintage music video"
      ]
    },
    {
      "id": "ukmrI7DlXkc",
      "title": "Soundie: In a Shanty in Old Shanty Town | 8K HQ (4K UHD) | Vintage Music Film | @remAIke_IT",
      "views": 2,
      "tags": [
        "1932",
        "1940s",
        "1940s music",
        "4K UHD",
        "8K",
        "Mills Novelty Company",
        "Official Audio",
        "Panoram",
        "Soundie",
        "Soundies",
        "big band",
        "big band music",
        "boogie woogie",
        "classic music",
        "golden age music",
        "jazz",
        "jazz music",
        "jazz standard",
        "jukebox",
        "music",
        "music video",
        "official video",
        "remAIke",
        "remastered",
        "restored",
        "retro music",
        "rhythm and blues",
        "shanty town",
        "song",
        "swing era",
        "swing music",
        "vintage music",
        "vintage music video"
      ]
    },
    {
      "id": "oA7XcqVM1Vo",
      "title": "Soundie: I Cant Give You Anything But Love | 8K HQ (4K UHD) | Vintage Music Film | @remAIke_IT",
      "views": 2,
      "tags": [
        "1928",
        "1940s",
        "1940s music",
        "4K UHD",
        "8K",
        "Dorothy Fields",
        "Jimmy McHugh",
        "Mills Novelty Company",
        "Official Audio",
        "Panoram",
        "Soundie",
        "Soundies",
        "big band",
        "big band music",
        "boogie woogie",
        "classic music",
        "golden age music",
        "jazz",
        "jazz music",
        "jazz standard",
        "jukebox",
        "music",
        "music video",
        "official video",
        "remAIke",
        "remastered",
        "restored",
        "retro music",
        "rhythm and blues",
        "song",
        "swing era",
        "swing music",
        "vintage music",
        "vintage music video"
      ]
    },
    {
      "id": "OvBqUlzTunI",
      "title": "Soundie: Hollywood Boogie | 8K HQ (4K UHD) | Vintage Music Film | @remAIke_IT",
      "views": 1,
      "tags": [
        "1940s",
        "1940s music",
        "4K UHD",
        "8K",
        "Hadda Brooks",
        "Mills Novelty Company",
        "Official Audio",
        "Panoram",
        "Queen of Boogie",
        "R&B",
        "Soundie",
        "Soundies",
        "big band",
        "big band music",
        "boogie woogie",
        "classic music",
        "golden age music",
        "jazz",
        "jazz music",
        "jazz standard",
        "jukebox",
        "music",
        "music video",
        "official video",
        "piano",
        "remAIke",
        "remastered",
        "restored",
        "retro music",
        "rhythm and blues",
        "song",
        "swing era",
        "swing music",
        "vintage music",
        "vintage music video"
      ]
    },
    {
      "id": "mDSdzFc572Y",
      "title": "Soundie: What This Country Needs | 8K HQ (4K UHD) | Vintage Music Film | @remAIke_IT",
      "views": 0,
      "tags": [
        "1940s",
        "1940s music",
        "4K UHD",
        "8K",
        "Mills Novelty Company",
        "Official Audio",
        "Panoram",
        "Soundie",
        "Soundies",
        "big band",
        "big band music",
        "boogie woogie",
        "classic music",
        "comedy",
        "golden age music",
        "jazz",
        "jazz music",
        "jazz standard",
        "jukebox",
        "music",
        "music video",
        "novelty song",
        "official video",
        "remAIke",
        "remastered",
        "restored",
        "retro music",
        "rhythm and blues",
        "song",
        "swing era",
        "swing music",
        "vintage music",
        "vintage music video"
      ]
    },
    {
      "id": "hAs6lunYl-E",
      "title": "Soundie: A Jazz Etude | 8K HQ (4K UHD) | Vintage Music Film | @remAIke_IT",
      "views": 2,
      "tags": [
        "1940s",
        "1940s music",
        "4K UHD",
        "8K",
        "Mills Novelty Company",
        "Official Audio",
        "Panoram",
        "Soundie",
        "Soundies",
        "big band",
        "big band music",
        "boogie woogie",
        "classic music",
        "etude",
        "golden age music",
        "instrumental",
        "jazz",
        "jazz music",
        "jazz standard",
        "jukebox",
        "music",
        "music video",
        "official video",
        "remAIke",
        "remastered",
        "restored",
        "retro music",
        "rhythm and blues",
        "song",
        "swing era",
        "swing music",
        "vintage music",
        "vintage music video"
      ]
    },
    {
      "id": "1zKpqdriv70",
      "title": "Soundie: Ten Pretty Girls | 8K HQ (4K UHD) | Vintage Music Film | @remAIke_IT",
      "views": 1,
      "tags": [
        "1940s",
        "1940s music",
        "4K UHD",
        "8K",
        "Mills Novelty Company",
        "Official Audio",
        "Panoram",
        "Soundie",
        "Soundies",
        "big band",
        "big band music",
        "boogie woogie",
        "classic music",
        "dance",
        "girls",
        "golden age music",
        "jazz",
        "jazz music",
        "jazz standard",
        "jukebox",
        "music",
        "music video",
        "official video",
        "remAIke",
        "remastered",
        "restored",
        "retro music",
        "rhythm and blues",
        "showgirls",
        "song",
        "swing era",
        "swing music",
        "vintage music",
        "vintage music video"
      ]
    },
    {
      "id": "Z2SxppvCWvE",
      "title": "Soundie: Hawaiian Hula Song | 8K HQ (4K UHD) | Vintage Music Film | @remAIke_IT",
      "views": 2,
      "tags": [
        "1940s",
        "1940s music",
        "4K UHD",
        "8K",
        "Hawaiian",
        "Mills Novelty Company",
        "Official Audio",
        "Panoram",
        "Soundie",
        "Soundies",
        "big band",
        "big band music",
        "boogie woogie",
        "classic music",
        "golden age music",
        "hula",
        "island music",
        "jazz",
        "jazz music",
        "jazz standard",
        "jukebox",
        "music",
        "music video",
        "official video",
        "remAIke",
        "remastered",
        "restored",
        "retro music",
        "rhythm and blues",
        "song",
        "swing era",
        "swing music",
        "tropical",
        "ukulele",
        "vintage music",
        "vintage music video"
      ]
    },
    {
      "id": "rprpMDyTWRI",
      "title": "Soundie: Zig Me Baby with a Gentle Zag | 8K HQ (4K UHD) | Vintage Music Film | @remAIke_IT",
      "views": 0,
      "tags": [
        "1940s",
        "1940s music",
        "4K UHD",
        "8K",
        "Mills Novelty Company",
        "Official Audio",
        "Panoram",
        "Soundie",
        "Soundies",
        "big band",
        "big band music",
        "boogie woogie",
        "classic music",
        "dance",
        "golden age music",
        "jazz",
        "jazz music",
        "jazz standard",
        "jukebox",
        "music",
        "music video",
        "novelty",
        "official video",
        "remAIke",
        "remastered",
        "restored",
        "retro music",
        "rhythm and blues",
        "song",
        "swing",
        "swing era",
        "swing music",
        "vintage music",
        "vintage music video"
      ]
    },
    {
      "id": "NAk0QvvaT7M",
      "title": "Soundie: Whos Yehudi | 8K HQ (4K UHD) | Vintage Music Film | @remAIke_IT",
      "views": 0,
      "tags": [
        "1940s",
        "1940s music",
        "4K UHD",
        "8K",
        "Mills Novelty Company",
        "Official Audio",
        "Panoram",
        "Soundie",
        "Soundies",
        "Yehudi Menuhin",
        "big band",
        "big band music",
        "boogie woogie",
        "classic music",
        "comedy",
        "golden age music",
        "jazz",
        "jazz music",
        "jazz standard",
        "jukebox",
        "music",
        "music video",
        "novelty",
        "official video",
        "remAIke",
        "remastered",
        "restored",
        "retro music",
        "rhythm and blues",
        "song",
        "swing era",
        "swing music",
        "vintage music",
        "vintage music video"
      ]
    },
    {
      "id": "w82vzaGBqwE",
      "title": "Soundie: A Little Robin Told Me So | 8K HQ (4K UHD) | Vintage Music Film | @remAIke_IT",
      "views": 2,
      "tags": [
        "1940s",
        "1940s music",
        "4K UHD",
        "8K",
        "Mills Novelty Company",
        "Official Audio",
        "Panoram",
        "Soundie",
        "Soundies",
        "big band",
        "big band music",
        "bird",
        "boogie woogie",
        "classic music",
        "golden age music",
        "jazz",
        "jazz music",
        "jazz standard",
        "jukebox",
        "music",
        "music video",
        "official video",
        "remAIke",
        "remastered",
        "restored",
        "retro music",
        "rhythm and blues",
        "robin",
        "romantic",
        "song",
        "spring",
        "swing era",
        "swing music",
        "vintage music",
        "vintage music video"
      ]
    },
    {
      "id": "GerP7_evS9o",
      "title": "Soundie: Beyond the Blue Horizon | 8K HQ (4K UHD) | Vintage Music Film | @remAIke_IT",
      "views": 1,
      "tags": [
        "1930",
        "1940s",
        "1940s music",
        "4K UHD",
        "8K",
        "Jeanette MacDonald",
        "Leo Robin",
        "Mills Novelty Company",
        "Official Audio",
        "Panoram",
        "Richard Whiting",
        "Soundie",
        "Soundies",
        "big band",
        "big band music",
        "boogie woogie",
        "classic music",
        "golden age music",
        "jazz",
        "jazz music",
        "jazz standard",
        "jukebox",
        "music",
        "music video",
        "official video",
        "remAIke",
        "remastered",
        "restored",
        "retro music",
        "rhythm and blues",
        "song",
        "swing era",
        "swing music",
        "vintage music",
        "vintage music video"
      ]
    },
    {
      "id": "D-LL4VuR5Pg",
      "title": "Soundie: Lullaby of Broadway | 8K HQ (4K UHD) | Vintage Music Film | @remAIke_IT",
      "views": 0,
      "tags": [
        "1940s",
        "1940s music",
        "4K UHD",
        "8K",
        "AI upscaled",
        "Lullaby of Broadway",
        "big band",
        "classic music",
        "jazz",
        "jukebox",
        "music video",
        "nostalgia",
        "panoram",
        "public domain",
        "remAIke",
        "remastered",
        "retro",
        "soundie",
        "soundies",
        "swing",
        "vintage music"
      ]
    },
    {
      "id": "LJp-M01OI-8",
      "title": "Soundie: Chime Bells | 8K HQ (4K UHD) | Vintage Music Film | @remAIke_IT",
      "views": 1,
      "tags": [
        "1940s",
        "1940s music",
        "4K UHD",
        "8K",
        "AI upscaled",
        "Chime Bells",
        "big band",
        "classic music",
        "jazz",
        "jukebox",
        "music video",
        "nostalgia",
        "panoram",
        "public domain",
        "remAIke",
        "remastered",
        "retro",
        "soundie",
        "soundies",
        "swing",
        "vintage music"
      ]
    },
    {
      "id": "HvwtRYp43eU",
      "title": "Soundie: Got to Be This or That | 8K HQ (4K UHD) | Vintage Music Film | @remAIke_IT",
      "views": 2,
      "tags": [
        "1940s",
        "1940s music",
        "4K UHD",
        "8K",
        "AI upscaled",
        "Got to Be This or That",
        "big band",
        "classic music",
        "jazz",
        "jukebox",
        "music video",
        "nostalgia",
        "panoram",
        "public domain",
        "remAIke",
        "remastered",
        "retro",
        "soundie",
        "soundies",
        "swing",
        "vintage music"
      ]
    },
    {
      "id": "2yGX3wy-4SQ",
      "title": "Soundie: Havana Madrid Show | 8K HQ (4K UHD) | Vintage Music Film | @remAIke_IT",
      "views": 3,
      "tags": [
        "1940s",
        "1940s music",
        "4K UHD",
        "8K",
        "AI upscaled",
        "Havana Madrid Show",
        "big band",
        "classic music",
        "jazz",
        "jukebox",
        "music video",
        "nostalgia",
        "panoram",
        "public domain",
        "remAIke",
        "remastered",
        "retro",
        "soundie",
        "soundies",
        "swing",
        "vintage music"
      ]
    },
    {
      "id": "hIsTWWP-YkQ",
      "title": "Soundie: Once in a While | 8K HQ (4K UHD) | Vintage Music Film | @remAIke_IT",
      "views": 12,
      "tags": [
        "1940s",
        "1940s music",
        "4K UHD",
        "8K",
        "AI upscaled",
        "Once in a While",
        "big band",
        "classic music",
        "jazz",
        "jukebox",
        "music video",
        "nostalgia",
        "panoram",
        "public domain",
        "remAIke",
        "remastered",
        "retro",
        "soundie",
        "soundies",
        "swing",
        "vintage music"
      ]
    },
    {
      "id": "mReDNz-Exdk",
      "title": "Soundie: Lamp of Memory | 8K HQ (4K UHD) | Vintage Music Film | @remAIke_IT",
      "views": 10,
      "tags": [
        "1940s",
        "1940s music",
        "4K UHD",
        "8K",
        "AI upscaled",
        "Lamp of Memory",
        "big band",
        "classic music",
        "jazz",
        "jukebox",
        "music video",
        "nostalgia",
        "panoram",
        "public domain",
        "remAIke",
        "remastered",
        "retro",
        "soundie",
        "soundies",
        "swing",
        "vintage music"
      ]
    },
    {
      "id": "6XVj6G3qNYY",
      "title": "Soundie: Jiveroo | 8K HQ (4K UHD) | Vintage Music Film | @remAIke_IT",
      "views": 5,
      "tags": [
        "1940s",
        "1940s music",
        "4K UHD",
        "8K",
        "Mills Novelty Company",
        "Official Audio",
        "Panoram",
        "Soundie",
        "Soundies",
        "big band",
        "big band music",
        "boogie woogie",
        "classic music",
        "dance",
        "golden age music",
        "jazz",
        "jazz music",
        "jazz standard",
        "jive",
        "jukebox",
        "music",
        "music video",
        "official video",
        "remAIke",
        "remastered",
        "restored",
        "retro music",
        "rhythm and blues",
        "song",
        "swing dance",
        "swing era",
        "swing music",
        "vintage music",
        "vintage music video"
      ]
    },
    {
      "id": "ukmrI7DlXkc",
      "title": "Soundie: In a Shanty in Old Shanty Town | 8K HQ (4K UHD) | Vintage Music Film | @remAIke_IT",
      "views": 2,
      "tags": [
        "1932",
        "1940s",
        "1940s music",
        "4K UHD",
        "8K",
        "Mills Novelty Company",
        "Official Audio",
        "Panoram",
        "Soundie",
        "Soundies",
        "big band",
        "big band music",
        "boogie woogie",
        "classic music",
        "golden age music",
        "jazz",
        "jazz music",
        "jazz standard",
        "jukebox",
        "music",
        "music video",
        "official video",
        "remAIke",
        "remastered",
        "restored",
        "retro music",
        "rhythm and blues",
        "shanty town",
        "song",
        "swing era",
        "swing music",
        "vintage music",
        "vintage music video"
      ]
    },
    {
      "id": "oA7XcqVM1Vo",
      "title": "Soundie: I Cant Give You Anything But Love | 8K HQ (4K UHD) | Vintage Music Film | @remAIke_IT",
      "views": 2,
      "tags": [
        "1928",
        "1940s",
        "1940s music",
        "4K UHD",
        "8K",
        "Dorothy Fields",
        "Jimmy McHugh",
        "Mills Novelty Company",
        "Official Audio",
        "Panoram",
        "Soundie",
        "Soundies",
        "big band",
        "big band music",
        "boogie woogie",
        "classic music",
        "golden age music",
        "jazz",
        "jazz music",
        "jazz standard",
        "jukebox",
        "music",
        "music video",
        "official video",
        "remAIke",
        "remastered",
        "restored",
        "retro music",
        "rhythm and blues",
        "song",
        "swing era",
        "swing music",
        "vintage music",
        "vintage music video"
      ]
    },
    {
      "id": "OvBqUlzTunI",
      "title": "Soundie: Hollywood Boogie | 8K HQ (4K UHD) | Vintage Music Film | @remAIke_IT",
      "views": 1,
      "tags": [
        "1940s",
        "1940s music",
        "4K UHD",
        "8K",
        "Hadda Brooks",
        "Mills Novelty Company",
        "Official Audio",
        "Panoram",
        "Queen of Boogie",
        "R&B",
        "Soundie",
        "Soundies",
        "big band",
        "big band music",
        "boogie woogie",
        "classic music",
        "golden age music",
        "jazz",
        "jazz music",
        "jazz standard",
        "jukebox",
        "music",
        "music video",
        "official video",
        "piano",
        "remAIke",
        "remastered",
        "restored",
        "retro music",
        "rhythm and blues",
        "song",
        "swing era",
        "swing music",
        "vintage music",
        "vintage music video"
      ]
    },
    {
      "id": "mDSdzFc572Y",
      "title": "Soundie: What This Country Needs | 8K HQ (4K UHD) | Vintage Music Film | @remAIke_IT",
      "views": 0,
      "tags": [
        "1940s",
        "1940s music",
        "4K UHD",
        "8K",
        "Mills Novelty Company",
        "Official Audio",
        "Panoram",
        "Soundie",
        "Soundies",
        "big band",
        "big band music",
        "boogie woogie",
        "classic music",
        "comedy",
        "golden age music",
        "jazz",
        "jazz music",
        "jazz standard",
        "jukebox",
        "music",
        "music video",
        "novelty song",
        "official video",
        "remAIke",
        "remastered",
        "restored",
        "retro music",
        "rhythm and blues",
        "song",
        "swing era",
        "swing music",
        "vintage music",
        "vintage music video"
      ]
    },
    {
      "id": "hAs6lunYl-E",
      "title": "Soundie: A Jazz Etude | 8K HQ (4K UHD) | Vintage Music Film | @remAIke_IT",
      "views": 2,
      "tags": [
        "1940s",
        "1940s music",
        "4K UHD",
        "8K",
        "Mills Novelty Company",
        "Official Audio",
        "Panoram",
        "Soundie",
        "Soundies",
        "big band",
        "big band music",
        "boogie woogie",
        "classic music",
        "etude",
        "golden age music",
        "instrumental",
        "jazz",
        "jazz music",
        "jazz standard",
        "jukebox",
        "music",
        "music video",
        "official video",
        "remAIke",
        "remastered",
        "restored",
        "retro music",
        "rhythm and blues",
        "song",
        "swing era",
        "swing music",
        "vintage music",
        "vintage music video"
      ]
    },
    {
      "id": "1zKpqdriv70",
      "title": "Soundie: Ten Pretty Girls | 8K HQ (4K UHD) | Vintage Music Film | @remAIke_IT",
      "views": 1,
      "tags": [
        "1940s",
        "1940s music",
        "4K UHD",
        "8K",
        "Mills Novelty Company",
        "Official Audio",
        "Panoram",
        "Soundie",
        "Soundies",
        "big band",
        "big band music",
        "boogie woogie",
        "classic music",
        "dance",
        "girls",
        "golden age music",
        "jazz",
        "jazz music",
        "jazz standard",
        "jukebox",
        "music",
        "music video",
        "official video",
        "remAIke",
        "remastered",
        "restored",
        "retro music",
        "rhythm and blues",
        "showgirls",
        "song",
        "swing era",
        "swing music",
        "vintage music",
        "vintage music video"
      ]
    },
    {
      "id": "Z2SxppvCWvE",
      "title": "Soundie: Hawaiian Hula Song | 8K HQ (4K UHD) | Vintage Music Film | @remAIke_IT",
      "views": 2,
      "tags": [
        "1940s",
        "1940s music",
        "4K UHD",
        "8K",
        "Hawaiian",
        "Mills Novelty Company",
        "Official Audio",
        "Panoram",
        "Soundie",
        "Soundies",
        "big band",
        "big band music",
        "boogie woogie",
        "classic music",
        "golden age music",
        "hula",
        "island music",
        "jazz",
        "jazz music",
        "jazz standard",
        "jukebox",
        "music",
        "music video",
        "official video",
        "remAIke",
        "remastered",
        "restored",
        "retro music",
        "rhythm and blues",
        "song",
        "swing era",
        "swing music",
        "tropical",
        "ukulele",
        "vintage music",
        "vintage music video"
      ]
    },
    {
      "id": "rprpMDyTWRI",
      "title": "Soundie: Zig Me Baby with a Gentle Zag | 8K HQ (4K UHD) | Vintage Music Film | @remAIke_IT",
      "views": 0,
      "tags": [
        "1940s",
        "1940s music",
        "4K UHD",
        "8K",
        "Mills Novelty Company",
        "Official Audio",
        "Panoram",
        "Soundie",
        "Soundies",
        "big band",
        "big band music",
        "boogie woogie",
        "classic music",
        "dance",
        "golden age music",
        "jazz",
        "jazz music",
        "jazz standard",
        "jukebox",
        "music",
        "music video",
        "novelty",
        "official video",
        "remAIke",
        "remastered",
        "restored",
        "retro music",
        "rhythm and blues",
        "song",
        "swing",
        "swing era",
        "swing music",
        "vintage music",
        "vintage music video"
      ]
    },
    {
      "id": "NAk0QvvaT7M",
      "title": "Soundie: Whos Yehudi | 8K HQ (4K UHD) | Vintage Music Film | @remAIke_IT",
      "views": 0,
      "tags": [
        "1940s",
        "1940s music",
        "4K UHD",
        "8K",
        "Mills Novelty Company",
        "Official Audio",
        "Panoram",
        "Soundie",
        "Soundies",
        "Yehudi Menuhin",
        "big band",
        "big band music",
        "boogie woogie",
        "classic music",
        "comedy",
        "golden age music",
        "jazz",
        "jazz music",
        "jazz standard",
        "jukebox",
        "music",
        "music video",
        "novelty",
        "official video",
        "remAIke",
        "remastered",
        "restored",
        "retro music",
        "rhythm and blues",
        "song",
        "swing era",
        "swing music",
        "vintage music",
        "vintage music video"
      ]
    },
    {
      "id": "w82vzaGBqwE",
      "title": "Soundie: A Little Robin Told Me So | 8K HQ (4K UHD) | Vintage Music Film | @remAIke_IT",
      "views": 2,
      "tags": [
        "1940s",
        "1940s music",
        "4K UHD",
        "8K",
        "Mills Novelty Company",
        "Official Audio",
        "Panoram",
        "Soundie",
        "Soundies",
        "big band",
        "big band music",
        "bird",
        "boogie woogie",
        "classic music",
        "golden age music",
        "jazz",
        "jazz music",
        "jazz standard",
        "jukebox",
        "music",
        "music video",
        "official video",
        "remAIke",
        "remastered",
        "restored",
        "retro music",
        "rhythm and blues",
        "robin",
        "romantic",
        "song",
        "spring",
        "swing era",
        "swing music",
        "vintage music",
        "vintage music video"
      ]
    },
    {
      "id": "GerP7_evS9o",
      "title": "Soundie: Beyond the Blue Horizon | 8K HQ (4K UHD) | Vintage Music Film | @remAIke_IT",
      "views": 1,
      "tags": [
        "1930",
        "1940s",
        "1940s music",
        "4K UHD",
        "8K",
        "Jeanette MacDonald",
        "Leo Robin",
        "Mills Novelty Company",
        "Official Audio",
        "Panoram",
        "Richard Whiting",
        "Soundie",
        "Soundies",
        "big band",
        "big band music",
        "boogie woogie",
        "classic music",
        "golden age music",
        "jazz",
        "jazz music",
        "jazz standard",
        "jukebox",
        "music",
        "music video",
        "official video",
        "remAIke",
        "remastered",
        "restored",
        "retro music",
        "rhythm and blues",
        "song",
        "swing era",
        "swing music",
        "vintage music",
        "vintage music video"
      ]
    },
    {
      "id": "D-LL4VuR5Pg",
      "title": "Soundie: Lullaby of Broadway | 8K HQ (4K UHD) | Vintage Music Film | @remAIke_IT",
      "views": 0,
      "tags": [
        "1940s",
        "1940s music",
        "4K UHD",
        "8K",
        "AI upscaled",
        "Lullaby of Broadway",
        "big band",
        "classic music",
        "jazz",
        "jukebox",
        "music video",
        "nostalgia",
        "panoram",
        "public domain",
        "remAIke",
        "remastered",
        "retro",
        "soundie",
        "soundies",
        "swing",
        "vintage music"
      ]
    },
    {
      "id": "LJp-M01OI-8",
      "title": "Soundie: Chime Bells | 8K HQ (4K UHD) | Vintage Music Film | @remAIke_IT",
      "views": 1,
      "tags": [
        "1940s",
        "1940s music",
        "4K UHD",
        "8K",
        "AI upscaled",
        "Chime Bells",
        "big band",
        "classic music",
        "jazz",
        "jukebox",
        "music video",
        "nostalgia",
        "panoram",
        "public domain",
        "remAIke",
        "remastered",
        "retro",
        "soundie",
        "soundies",
        "swing",
        "vintage music"
      ]
    },
    {
      "id": "HvwtRYp43eU",
      "title": "Soundie: Got to Be This or That | 8K HQ (4K UHD) | Vintage Music Film | @remAIke_IT",
      "views": 2,
      "tags": [
        "1940s",
        "1940s music",
        "4K UHD",
        "8K",
        "AI upscaled",
        "Got to Be This or That",
        "big band",
        "classic music",
        "jazz",
        "jukebox",
        "music video",
        "nostalgia",
        "panoram",
        "public domain",
        "remAIke",
        "remastered",
        "retro",
        "soundie",
        "soundies",
        "swing",
        "vintage music"
      ]
    },
    {
      "id": "2yGX3wy-4SQ",
      "title": "Soundie: Havana Madrid Show | 8K HQ (4K UHD) | Vintage Music Film | @remAIke_IT",
      "views": 3,
      "tags": [
        "1940s",
        "1940s music",
        "4K UHD",
        "8K",
        "AI upscaled",
        "Havana Madrid Show",
        "big band",
        "classic music",
        "jazz",
        "jukebox",
        "music video",
        "nostalgia",
        "panoram",
        "public domain",
        "remAIke",
        "remastered",
        "retro",
        "soundie",
        "soundies",
        "swing",
        "vintage music"
      ]
    },
    {
      "id": "hIsTWWP-YkQ",
      "title": "Soundie: Once in a While | 8K HQ (4K UHD) | Vintage Music Film | @remAIke_IT",
      "views": 12,
      "tags": [
        "1940s",
        "1940s music",
        "4K UHD",
        "8K",
        "AI upscaled",
        "Once in a While",
        "big band",
        "classic music",
        "jazz",
        "jukebox",
        "music video",
        "nostalgia",
        "panoram",
        "public domain",
        "remAIke",
        "remastered",
        "retro",
        "soundie",
        "soundies",
        "swing",
        "vintage music"
      ]
    },
    {
      "id": "340C9lsoyYk",
      "title": "Soundie: Tica Ti Tica Ta | 8K HQ (4K UHD) | Vintage Music Film | @remAIke_IT",
      "views": 19,
      "tags": [
        "8K Music",
        "Cinematic Music",
        "Classic Soundies",
        "Film Nostalgia",
        "Golden Age Music",
        "HQ Soundie",
        "Music History",
        "Musical Cinema",
        "Nostalgic Tunes",
        "Old School Tunes",
        "Remastered Sound",
        "Retro Music Film",
        "Soundie Music",
        "Tica Ti Tica Ta",
        "Timeless Classics",
        "UHD Music",
        "Vintage Film",
        "Vintage Vibes",
        "Visual Jukebox"
      ]
    },
    {
      "id": "A8LWgWF5f5k",
      "title": "Soundie: The Hut-Sut Song | 8K HQ (4K UHD) | Vintage Music Film | @remAIke_IT",
      "views": 6,
      "tags": [
        "1940s Music",
        "8K Music",
        "Cinematic History",
        "Classic Soundies",
        "Film Nostalgia",
        "Golden Age",
        "Hut-Sut Song",
        "Jazz Film",
        "Music History",
        "Music Revival",
        "Musical Short",
        "Rare Clips",
        "Retro Tunes",
        "Short Film",
        "Soundie",
        "Soundie Archive",
        "UHD Music",
        "Vintage Film",
        "Vintage Music"
      ]
    },
    {
      "id": "DHogGPBbzRI",
      "title": "Soundie: Sweet Sue (Just You) | 8K HQ (4K UHD) | Vintage Music Film | @remAIke_IT",
      "views": 8,
      "tags": [
        "8K Video",
        "Classic Hits",
        "Dancing Clips",
        "Film Nostalgia",
        "Golden Age",
        "High Fidelity",
        "Jazz Era",
        "Music Film",
        "Musical Short",
        "Nostalgic Sounds",
        "Oldies But Goldies",
        "Remastered Audio",
        "Retro Tunes",
        "Soundie",
        "Sweet Sue",
        "Timeless Classics",
        "UHD Music",
        "Vintage Aesthetic",
        "Vintage Music"
      ]
    }
  ],
  "draft_videos": []
}